Lab3/src/comparator.v
module comparator (
    input  wire [1:0] A,        // 2-bit input A
    input  wire [1:0] B,        // 2-bit input B
    output reg  AGTB,           // A greater than B
    output reg  AEQB,           // A equal to B
    output reg  ALTB            // A less than B
);

    // Procedural combinational logic block
    always @(*) begin
        // Default outputs
        AGTB = 1'b0;
        AEQB = 1'b0;
        ALTB = 1'b0;
        
        // Compare A and B
        if (A > B) begin
            AGTB = 1'b1;
        end
        else if (A == B) begin
            AEQB = 1'b1;
        end
        else begin
            ALTB = 1'b1;
        end
    end

endmodule

Lab3/sim/tb_comparator.v
`timescale 1ns / 1ps

module tb_comparator;

    // Clock signal for synchronized version
    reg CLOCK_50;
    
    // Testbench signals
    reg  [1:0] A, B;
    wire AGTB, AEQB, ALTB;
    
    // Clock generation (50 MHz)
    initial begin
        CLOCK_50 = 0;
        forever #10 CLOCK_50 = ~CLOCK_50;  // 50 MHz clock
    end
    
    // Instantiate UUT (basic comparator)
    comparator uut (
        .A(A),
        .B(B),
        .AGTB(AGTB),
        .AEQB(AEQB),
        .ALTB(ALTB)
    );
    
    integer i, j;

    initial begin
        // Create VCD file for waveform viewing
        $dumpfile("comparator_waveform.vcd");
        $dumpvars(0, tb_comparator);
        
        // Display header
        $display("Time\tA\tB\tAGTB\tAEQB\tALTB");
        $display("-------------------------------");
        
        // Loop through all 16 combinations using nonblocking assignments
        for (i = 0; i < 4; i = i + 1) begin
            for (j = 0; j < 4; j = j + 1) begin
                A <= i[1:0];
                B <= j[1:0];
                
                // Wait one clock to see the change propagate
                @(posedge CLOCK_50);
                
                $display("%0t\t%0b\t%0b\t%b\t%b\t%b", 
                         $time, A, B, AGTB, AEQB, ALTB);
            end
        end
        
        $display("All combinations tested.");
        $finish;
    end

endmodule

Lab3/sim/comparator_waveform.vcd
$date
	Tue Sep 09 17:43:29 2025
$end
$version
	ModelSim Version 10.5b
$end
$timescale
	1ps
$end

$scope module tb_comparator $end
$var reg 1 ! CLOCK_50 $end
$var reg 2 " A [1:0] $end
$var reg 2 # B [1:0] $end
$var wire 1 $ AGTB $end
$var wire 1 % AEQB $end
$var wire 1 & ALTB $end
$var integer 32 ' i $end
$var integer 32 ( j $end

$scope module uut $end
$var wire 1 ) A [1] $end
$var wire 1 * A [0] $end
$var wire 1 + B [1] $end
$var wire 1 , B [0] $end
$var reg 1 - AGTB $end
$var reg 1 . AEQB $end
$var reg 1 / ALTB $end
$upscope $end
$upscope $end
$enddefinitions $end
#0
$dumpvars
0!
b0 "
b0 #
0-
1.
0/
b0 '
b0 (
0$
1%
0&
0,
0+
0*
0)
$end
#10000
1!
b1 (
b1 #
1,
0.
1/
0%
1&
#20000
0!
#30000
1!
b10 (
b10 #
0,
1+
0/
1/
#40000
0!
#50000
1!
b11 (
b11 #
1,
0/
1/
#60000
0!
#70000
1!
b100 (
b1 '
b0 (
b1 "
b0 #
0,
0+
1*
0/
1-
0&
1$
#80000
0!
#90000
1!
b1 (
b1 #
1,
0-
1.
0$
1%
#100000
0!
#110000
1!
b10 (
b10 #
0,
1+
0.
1/
0%
1&
#120000
0!
#130000
1!
b11 (
b11 #
1,
0/
1/
#140000
0!
#150000
1!
b100 (
b10 '
b0 (
b10 "
b0 #
0,
0+
0*
1)
0/
1-
0&
1$
#160000
0!
#170000
1!
b1 (
b1 #
1,
0-
1-
#180000
0!
#190000
1!
b10 (
b10 #
0,
1+
0-
1.
0$
1%
#200000
0!
#210000
1!
b11 (
b11 #
1,
0.
1/
0%
1&
#220000
0!
#230000
1!
b100 (
b11 '
b0 (
b11 "
b0 #
0,
0+
1*
0/
1-
0&
1$
#240000
0!
#250000
1!
b1 (
b1 #
1,
0-
1-
#260000
0!
#270000
1!
b10 (
b10 #
0,
1+
0-
1-
#280000
0!
#290000
1!
b11 (
b11 #
1,
0-
1.
0$
1%
#300000
0!
#310000
1!
b100 (
b100 '
